zuowen/__init__.py
zuowen/__main__.py
zuowen/data_parallel.py
zuowen/dataset.py
zuowen/generate.py
zuowen/preprocess.py
zuowen/run_ui.py
zuowen/train.py
zuowen/utils.py
zuowen/config/__init__.py
zuowen/config/cpm-medium.json
zuowen/config/cpm-small.json
zuowen/log/__init__.py
zuowen/ui/__init__.py
zuowen/ui/欢_欢迎.py
zuowen/ui/markdown/__init__.py
zuowen/ui/markdown/welcome.md
zuowen/ui/pages/0_作_作文生成器.py
zuowen/ui/pages/1_预_预先将作文整合为pkl文件.py
zuowen/ui/pages/2_训_训练获取你自己的预训练数据集.py
zuowen/vocab/chinese_vocab.model
zuowen/vocab/chinese_vocab.vocab
zuowen/vocab/vocab.json
zuowen-2022.6.29.post2.dist-info/LICENSE
zuowen-2022.6.29.post2.dist-info/METADATA
zuowen-2022.6.29.post2.dist-info/WHEEL
zuowen-2022.6.29.post2.dist-info/entry_points.txt
zuowen-2022.6.29.post2.dist-info/top_level.txt
zuowen-2022.6.29.post2.dist-info/RECORD
