Metadata-Version: 2.1
Name: zuowen
Version: 2022.6.29.post2
Summary: Python 作文生成器
Home-page: https://wufan.fun/
Author: Fan Wu
Author-email: admin@wufan.fun
Project-URL: Source Code, https://github.com/WindowsRegedit/zuowen
Keywords: UI CLI Torch Train Transformers Jieba SentencePiece
Classifier: Development Status :: 5 - Production/Stable
Classifier: Intended Audience :: Education
Classifier: License :: OSI Approved :: Apache Software License
Classifier: Programming Language :: Python :: 3.5
Classifier: Programming Language :: Python :: 3.6
Classifier: Programming Language :: Python :: 3.7
Classifier: Programming Language :: Python :: 3.8
Classifier: Programming Language :: Python :: 3.9
License-File: LICENSE
Requires-Dist: torch (==1.11.0)
Requires-Dist: transformers (==4.20.0)
Requires-Dist: jieba (==0.42.1)
Requires-Dist: sentencepiece (==0.1.96)
Requires-Dist: streamlit (==1.10.0)
Requires-Dist: tqdm (==4.64.0)
